stack_composed/__init__.py
stack_composed/image.py
stack_composed/parse.py
stack_composed/stack_composed_distributed.py
stack_composed/stack_composed_main.py
stack_composed/stats.py
stack_composed-25.3.data/scripts/stack-composed
stack_composed-25.3.dist-info/METADATA
stack_composed-25.3.dist-info/WHEEL
stack_composed-25.3.dist-info/top_level.txt
stack_composed-25.3.dist-info/RECORD
