Metadata-Version: 2.2
Name: stack-composed
Version: 25.3
Summary: Compute and generate the composed of a raster images stack
Home-page: https://github.com/SMByC/StackComposed
Author: Xavier C. Llano, SMBYC
Author-email: xavier.corredor.llano@gmail.com
License: GPLv3
Keywords: stack composed statistics landsat raster gis
Platform: Any
Classifier: Topic :: Scientific/Engineering :: GIS
Classifier: Intended Audience :: Science/Research
Classifier: Programming Language :: Python
Classifier: Environment :: Console
Classifier: License :: OSI Approved :: GNU General Public License v3 (GPLv3)
Requires-Dist: gdal
Requires-Dist: numpy
Requires-Dist: dask[array]
Requires-Dist: dask[bag]
Requires-Dist: cloudpickle
Dynamic: author
Dynamic: author-email
Dynamic: classifier
Dynamic: description
Dynamic: home-page
Dynamic: keywords
Dynamic: license
Dynamic: platform
Dynamic: requires-dist
Dynamic: summary
